README.md
pyproject.toml
setup.py
mobio/sdks/dataout/__init__.py
mobio_dataout_sdk_test.egg-info/PKG-INFO
mobio_dataout_sdk_test.egg-info/SOURCES.txt
mobio_dataout_sdk_test.egg-info/dependency_links.txt
mobio_dataout_sdk_test.egg-info/requires.txt
mobio_dataout_sdk_test.egg-info/top_level.txt